Metadata-Version: 1.0
Name: statdist
Version: 0.1
Summary: Basic statistical distributions in Python
Home-page: UNKNOWN
Author: Robert Smith
Author-email: rosmith731@yahoo.com
License: UNKNOWN
Platform: UNKNOWN
